meridian/__init__.py
meridian/py.typed
meridian/core/__init__.py
meridian/core/message.py
meridian/core/ports.py
meridian/core/scheduler.py
meridian/core/edge/__init__.py
meridian/core/edge/definition.py
meridian/core/node/__init__.py
meridian/core/node/base.py
meridian/core/policies/__init__.py
meridian/core/policies/definitions.py
meridian/core/priority_queue/__init__.py
meridian/core/priority_queue/config.py
meridian/core/priority_queue/processor.py
meridian/core/priority_queue/queue.py
meridian/core/runtime_plan/__init__.py
meridian/core/runtime_plan/plan.py
meridian/core/scheduler/__init__.py
meridian/core/scheduler/config.py
meridian/core/scheduler/coordinator.py
meridian/core/scheduler/execution.py
meridian/core/scheduler/fairness.py
meridian/core/scheduler/shutdown.py
meridian/core/subgraph/__init__.py
meridian/core/subgraph/construction.py
meridian/core/subgraph/execution.py
meridian/core/subgraph/management.py
meridian/core/subgraph/validation.py
meridian/nodes/__init__.py
meridian/nodes/base.py
meridian/nodes/consumers.py
meridian/nodes/controllers.py
meridian/nodes/data_processing.py
meridian/nodes/events.py
meridian/nodes/flow_control.py
meridian/nodes/monitoring.py
meridian/nodes/network.py
meridian/nodes/producers.py
meridian/nodes/state_management.py
meridian/nodes/storage.py
meridian/nodes/testing.py
meridian/nodes/transformers.py
meridian/nodes/workers.py
meridian/observability/__init__.py
meridian/observability/config.py
meridian/observability/logging/__init__.py
meridian/observability/logging/config.py
meridian/observability/logging/context.py
meridian/observability/logging/logger.py
meridian/observability/metrics/__init__.py
meridian/observability/metrics/collection.py
meridian/observability/metrics/config.py
meridian/observability/metrics/instruments.py
meridian/observability/metrics/providers.py
meridian/observability/tracing/__init__.py
meridian/observability/tracing/config.py
meridian/observability/tracing/context.py
meridian_runtime-1.2.0.dist-info/licenses/LICENSE
meridian_runtime-1.2.0.dist-info/METADATA
meridian_runtime-1.2.0.dist-info/WHEEL
meridian_runtime-1.2.0.dist-info/top_level.txt
meridian_runtime-1.2.0.dist-info/RECORD
