Metadata-Version: 2.4
Name: meridian-runtime
Version: 1.2.0
Summary: A minimal, reusable graph runtime for Python with bounded edges, fairness, and observability.
Author-email: GhostWeasel <devnull@ghostweasel.net>
License: BSD-3-Clause
Project-URL: Homepage, https://ghostweasellabs.github.io/meridian-runtime-docs
Project-URL: Repository, https://github.com/ghostweasellabs/meridian-runtime.git
Project-URL: Changelog, https://github.com/ghostweasellabs/meridian-runtime/blob/main/CHANGELOG.md
Project-URL: Documentation, https://ghostweasellabs.github.io/meridian-runtime-docs
Keywords: graph,runtime,scheduler,asyncio,observability,python
Classifier: Development Status :: 5 - Production/Stable
Classifier: License :: OSI Approved :: BSD License
Classifier: Programming Language :: Python :: 3
Classifier: Programming Language :: Python :: 3.11
Classifier: Programming Language :: Python :: 3 :: Only
Classifier: Intended Audience :: Developers
Classifier: Topic :: Software Development :: Libraries
Classifier: Topic :: System :: Distributed Computing
Classifier: Typing :: Typed
Requires-Python: >=3.11
License-File: LICENSE
Requires-Dist: jupytext>=1.17.2
Requires-Dist: mkdocs>=1.6.1
Requires-Dist: mkdocs-material>=9.6.16
Requires-Dist: cryptography>=42.0.0
Provides-Extra: dev
Requires-Dist: ruff<1.0.0,>=0.5.0; extra == "dev"
Requires-Dist: black<25.0.0,>=24.4.0; extra == "dev"
Requires-Dist: mypy<2.0.0,>=1.10.0; extra == "dev"
Requires-Dist: pytest<9.0.0,>=8.2.0; extra == "dev"
Requires-Dist: pytest-cov<6.0.0,>=5.0.0; extra == "dev"
Requires-Dist: types-setuptools>=75.0.0.0; extra == "dev"
Requires-Dist: types-toml>=0.10.8.20240310; extra == "dev"
Provides-Extra: notebooks
Requires-Dist: jupyter>=1.0.0; extra == "notebooks"
Requires-Dist: ipywidgets>=8.0.0; extra == "notebooks"
Requires-Dist: matplotlib>=3.5.0; extra == "notebooks"
Requires-Dist: plotly>=5.0.0; extra == "notebooks"
Requires-Dist: pandas>=1.5.0; extra == "notebooks"
Requires-Dist: seaborn>=0.11.0; extra == "notebooks"
Requires-Dist: networkx>=2.8.0; extra == "notebooks"
Requires-Dist: graphviz>=0.20.0; extra == "notebooks"
Dynamic: license-file
